{
    "href": "https://poscodx-auto.gooddi.lab:443/vco/api/actions/1d80591f-fa82-475a-be6b-572c0d33980a/",
    "relations": {
        "link": [
            {
                "href": "https://poscodx-auto.gooddi.lab:443/vco/api/actions/com.gvp.bp.vm.action/getCpuByMachineInstanceAndResourceId/",
                "rel": "alternate"
            },
            {
                "href": "https://poscodx-auto.gooddi.lab:443/vco/api/actions/1d80591f-fa82-475a-be6b-572c0d33980a/permissions/",
                "rel": "permissions"
            },
            {
                "href": "https://poscodx-auto.gooddi.lab:443/vco/api/actions/1d80591f-fa82-475a-be6b-572c0d33980a/executions/",
                "rel": "executions"
            }
        ]
    },
    "id": "1d80591f-fa82-475a-be6b-572c0d33980a",
    "input-parameters": [
        {
            "description": "",
            "type": "string",
            "name": "machineInstance"
        },
        {
            "description": "",
            "type": "string",
            "name": "resourceId"
        }
    ],
    "output-type": "number",
    "name": "getCpuByMachineInstanceAndResourceId",
    "module": "com.gvp.bp.vm.action",
    "version": "0.0.0",
    "fqn": "com.gvp.bp.vm.action/getCpuByMachineInstanceAndResourceId",
    "script": "",
    "bundleHasContent": false,
    "runtimeMemoryLimit": 0,
    "runtimeTimeout": 0
}